[
  {
    "city": "Phoenix",
    "state": "Arizona",
    "country": "USA",
    "lat": 33.4484,
    "lng": -112.074,
    "city_key": "usa|arizona|phoenix"
  },
  {
    "city": "San Francisco",
    "state": "California",
    "country": "USA",
    "lat": 37.7749,
    "lng": -122.4194,
    "city_key": "usa|california|san francisco"
  },
  {
    "city": "Los Angeles",
    "state": "California",
    "country": "USA",
    "lat": 34.0522,
    "lng": -118.2437,
    "city_key": "usa|california|los angeles"
  },
  {
    "city": "Austin",
    "state": "Texas",
    "country": "USA",
    "lat": 30.2672,
    "lng": -97.7431,
    "city_key": "usa|texas|austin"
  },
  {
    "city": "Miami",
    "state": "Florida",
    "country": "USA",
    "lat": 25.7617,
    "lng": -80.1918,
    "city_key": "usa|florida|miami"
  },
  {
    "city": "Houston",
    "state": "Texas",
    "country": "USA",
    "lat": 29.7604,
    "lng": -95.3698,
    "city_key": "usa|texas|houston"
  },
  {
    "city": "Mountain View",
    "state": "California",
    "country": "USA",
    "lat": 37.3861,
    "lng": -122.0839,
    "city_key": "usa|california|mountain view"
  },
  {
    "city": "Chicago",
    "state": "Illinois",
    "country": "USA",
    "lat": 41.8781,
    "lng": -87.6298,
    "city_key": "usa|illinois|chicago"
  },
  {
    "city": "Las Vegas",
    "state": "Nevada",
    "country": "USA",
    "lat": 36.1699,
    "lng": -115.1398,
    "city_key": "usa|nevada|las vegas"
  },
  {
    "city": "Foster City",
    "state": "California",
    "country": "USA",
    "lat": 37.5585,
    "lng": -122.2711,
    "city_key": "usa|california|foster city"
  },
  {
    "city": "Washington",
    "state": "District of Columbia",
    "country": "USA",
    "lat": 38.9072,
    "lng": -77.0369,
    "city_key": "usa|district of columbia|washington"
  },
  {
    "city": "Pittsburgh",
    "state": "Pennsylvania",
    "country": "USA",
    "lat": 40.4406,
    "lng": -79.9959,
    "city_key": "usa|pennsylvania|pittsburgh"
  },
  {
    "city": "Berkeley",
    "state": "California",
    "country": "USA",
    "lat": 37.8715,
    "lng": -122.273,
    "city_key": "usa|california|berkeley"
  },
  {
    "city": "Dallas",
    "state": "Texas",
    "country": "USA",
    "lat": 32.7767,
    "lng": -96.797,
    "city_key": "usa|texas|dallas"
  },
  {
    "city": "Tempe",
    "state": "Arizona",
    "country": "USA",
    "lat": 33.4255,
    "lng": -111.94,
    "city_key": "usa|arizona|tempe"
  },
  {
    "city": "Fairfax",
    "state": "Virginia",
    "country": "USA",
    "lat": 38.8462,
    "lng": -77.3064,
    "city_key": "usa|virginia|fairfax"
  },
  {
    "city": "Guangzhou",
    "state": "Guangdong",
    "country": "China",
    "lat": 23.1291,
    "lng": 113.2644,
    "city_key": "china|guangdong|guangzhou"
  },
  {
    "city": "Shenzhen",
    "state": "Guangdong",
    "country": "China",
    "lat": 22.5431,
    "lng": 114.0579,
    "city_key": "china|guangdong|shenzhen"
  },
  {
    "city": "Beijing",
    "state": "Beijing",
    "country": "China",
    "lat": 39.9042,
    "lng": 116.4074,
    "city_key": "china|beijing|beijing"
  },
  {
    "city": "Wuhan",
    "state": "Hubei",
    "country": "China",
    "lat": 30.5928,
    "lng": 114.3055,
    "city_key": "china|hubei|wuhan"
  },
  {
    "city": "Chongqing",
    "state": "Chongqing",
    "country": "China",
    "lat": 29.4316,
    "lng": 106.9123,
    "city_key": "china|chongqing|chongqing"
  },
  {
    "city": "Shanghai",
    "state": "Shanghai",
    "country": "China",
    "lat": 31.2304,
    "lng": 121.4737,
    "city_key": "china|shanghai|shanghai"
  },
  {
    "city": "Milton Keynes",
    "state": "England",
    "country": "UK",
    "lat": 52.0406,
    "lng": -0.7594,
    "city_key": "uk|england|milton keynes"
  },
  {
    "city": "Hamburg",
    "state": "Hamburg",
    "country": "Germany",
    "lat": 53.5511,
    "lng": 9.9937,
    "city_key": "germany|hamburg|hamburg"
  },
  {
    "city": "Oslo",
    "state": "Oslo",
    "country": "Norway",
    "lat": 59.9139,
    "lng": 10.7522,
    "city_key": "norway|oslo|oslo"
  },
  {
    "city": "Paris",
    "state": "Ile-de-France",
    "country": "France",
    "lat": 48.8566,
    "lng": 2.3522,
    "city_key": "france|ile-de-france|paris"
  },
  {
    "city": "Toronto",
    "state": "Ontario",
    "country": "Canada",
    "lat": 43.6532,
    "lng": -79.3832,
    "city_key": "canada|ontario|toronto"
  },
  {
    "city": "Vancouver",
    "state": "British Columbia",
    "country": "Canada",
    "lat": 49.2827,
    "lng": -123.1207,
    "city_key": "canada|british columbia|vancouver"
  },
  {
    "city": "Calgary",
    "state": "Alberta",
    "country": "Canada",
    "lat": 51.0447,
    "lng": -114.0719,
    "city_key": "canada|alberta|calgary"
  },
  {
    "city": "Edmonton",
    "state": "Alberta",
    "country": "Canada",
    "lat": 53.5461,
    "lng": -113.4938,
    "city_key": "canada|alberta|edmonton"
  },
  {
    "city": "Delhi",
    "state": "Delhi",
    "country": "India",
    "lat": 28.6139,
    "lng": 77.209,
    "city_key": "india|delhi|delhi"
  },
  {
    "city": "Bengaluru",
    "state": "Karnataka",
    "country": "India",
    "lat": 12.9716,
    "lng": 77.5946,
    "city_key": "india|karnataka|bengaluru"
  },
  {
    "city": "Mumbai",
    "state": "Maharashtra",
    "country": "India",
    "lat": 19.076,
    "lng": 72.8777,
    "city_key": "india|maharashtra|mumbai"
  },
  {
    "city": "Tokyo",
    "state": "Tokyo",
    "country": "Japan",
    "lat": 35.6762,
    "lng": 139.6503,
    "city_key": "japan|tokyo|tokyo"
  },
  {
    "city": "Osaka",
    "state": "Osaka",
    "country": "Japan",
    "lat": 34.6937,
    "lng": 135.5023,
    "city_key": "japan|osaka|osaka"
  },
  {
    "city": "City-UAE-1",
    "state": "Abu Dhabi",
    "country": "UAE",
    "lat": -68.4566,
    "lng": -78.0495,
    "city_key": "uae|abu dhabi|city-uae-1"
  },
  {
    "city": "City-Canada-2",
    "state": "Quebec",
    "country": "Canada",
    "lat": 4.2788,
    "lng": 57.0143,
    "city_key": "canada|quebec|city-canada-2"
  },
  {
    "city": "City-Japan-3",
    "state": "Osaka",
    "country": "Japan",
    "lat": 52.8691,
    "lng": -41.0064,
    "city_key": "japan|osaka|city-japan-3"
  },
  {
    "city": "City-Singapore-4",
    "state": "Singapore",
    "country": "Singapore",
    "lat": 66.2017,
    "lng": -29.4948,
    "city_key": "singapore|singapore|city-singapore-4"
  },
  {
    "city": "City-UK-5",
    "state": "Scotland",
    "country": "UK",
    "lat": -64.1033,
    "lng": -42.0361,
    "city_key": "uk|scotland|city-uk-5"
  },
  {
    "city": "City-Australia-6",
    "state": "Victoria",
    "country": "Australia",
    "lat": 33.4133,
    "lng": 44.2712,
    "city_key": "australia|victoria|city-australia-6"
  },
  {
    "city": "City-Singapore-7",
    "state": "Singapore",
    "country": "Singapore",
    "lat": 35.1487,
    "lng": 163.475,
    "city_key": "singapore|singapore|city-singapore-7"
  },
  {
    "city": "City-Canada-8",
    "state": "British Columbia",
    "country": "Canada",
    "lat": -49.197,
    "lng": 9.1849,
    "city_key": "canada|british columbia|city-canada-8"
  },
  {
    "city": "City-SouthKorea-9",
    "state": "Seoul",
    "country": "South Korea",
    "lat": 12.8271,
    "lng": -25.9979,
    "city_key": "south korea|seoul|city-southkorea-9"
  },
  {
    "city": "City-Singapore-10",
    "state": "Singapore",
    "country": "Singapore",
    "lat": 25.8235,
    "lng": -39.1514,
    "city_key": "singapore|singapore|city-singapore-10"
  },
  {
    "city": "City-China-11",
    "state": "Guangdong",
    "country": "China",
    "lat": 58.6462,
    "lng": -87.147,
    "city_key": "china|guangdong|city-china-11"
  },
  {
    "city": "City-Germany-12",
    "state": "Hesse",
    "country": "Germany",
    "lat": 14.4667,
    "lng": -64.7085,
    "city_key": "germany|hesse|city-germany-12"
  },
  {
    "city": "City-Germany-13",
    "state": "Berlin",
    "country": "Germany",
    "lat": 61.4568,
    "lng": -151.0674,
    "city_key": "germany|berlin|city-germany-13"
  },
  {
    "city": "City-SouthKorea-14",
    "state": "Seoul",
    "country": "South Korea",
    "lat": 4.97,
    "lng": 141.7545,
    "city_key": "south korea|seoul|city-southkorea-14"
  },
  {
    "city": "City-USA-15",
    "state": "Arizona",
    "country": "USA",
    "lat": -47.4955,
    "lng": 81.6846,
    "city_key": "usa|arizona|city-usa-15"
  },
  {
    "city": "City-India-16",
    "state": "Karnataka",
    "country": "India",
    "lat": -34.2432,
    "lng": 152.2961,
    "city_key": "india|karnataka|city-india-16"
  },
  {
    "city": "City-Brazil-17",
    "state": "Sao Paulo",
    "country": "Brazil",
    "lat": 42.8165,
    "lng": -149.7782,
    "city_key": "brazil|sao paulo|city-brazil-17"
  },
  {
    "city": "City-India-18",
    "state": "Karnataka",
    "country": "India",
    "lat": -36.8091,
    "lng": 63.009,
    "city_key": "india|karnataka|city-india-18"
  },
  {
    "city": "City-UK-19",
    "state": "England",
    "country": "UK",
    "lat": -50.6783,
    "lng": 145.9213,
    "city_key": "uk|england|city-uk-19"
  },
  {
    "city": "City-USA-20",
    "state": "Washington",
    "country": "USA",
    "lat": 35.984,
    "lng": 169.8762,
    "city_key": "usa|washington|city-usa-20"
  },
  {
    "city": "City-Germany-21",
    "state": "Hesse",
    "country": "Germany",
    "lat": 12.3107,
    "lng": -56.3606,
    "city_key": "germany|hesse|city-germany-21"
  },
  {
    "city": "City-Japan-22",
    "state": "Tokyo",
    "country": "Japan",
    "lat": 51.1976,
    "lng": -79.6129,
    "city_key": "japan|tokyo|city-japan-22"
  },
  {
    "city": "City-France-23",
    "state": "Auvergne-Rhone-Alpes",
    "country": "France",
    "lat": 6.3589,
    "lng": 94.7227,
    "city_key": "france|auvergne-rhone-alpes|city-france-23"
  },
  {
    "city": "City-Japan-24",
    "state": "Tokyo",
    "country": "Japan",
    "lat": 7.9812,
    "lng": -120.9667,
    "city_key": "japan|tokyo|city-japan-24"
  },
  {
    "city": "City-USA-25",
    "state": "Florida",
    "country": "USA",
    "lat": -63.1065,
    "lng": -94.3029,
    "city_key": "usa|florida|city-usa-25"
  },
  {
    "city": "City-Canada-26",
    "state": "Ontario",
    "country": "Canada",
    "lat": -22.0053,
    "lng": 119.5574,
    "city_key": "canada|ontario|city-canada-26"
  },
  {
    "city": "City-Brazil-27",
    "state": "Rio de Janeiro",
    "country": "Brazil",
    "lat": -31.1489,
    "lng": -61.8131,
    "city_key": "brazil|rio de janeiro|city-brazil-27"
  },
  {
    "city": "City-Germany-28",
    "state": "Hamburg",
    "country": "Germany",
    "lat": 45.6649,
    "lng": -85.4225,
    "city_key": "germany|hamburg|city-germany-28"
  },
  {
    "city": "City-Singapore-29",
    "state": "Singapore",
    "country": "Singapore",
    "lat": 22.5952,
    "lng": 73.4767,
    "city_key": "singapore|singapore|city-singapore-29"
  },
  {
    "city": "City-China-30",
    "state": "Shanghai",
    "country": "China",
    "lat": 2.6441,
    "lng": 99.4889,
    "city_key": "china|shanghai|city-china-30"
  },
  {
    "city": "City-Australia-31",
    "state": "Victoria",
    "country": "Australia",
    "lat": -28.9251,
    "lng": -105.2943,
    "city_key": "australia|victoria|city-australia-31"
  },
  {
    "city": "City-UAE-32",
    "state": "Abu Dhabi",
    "country": "UAE",
    "lat": -34.3052,
    "lng": 146.9798,
    "city_key": "uae|abu dhabi|city-uae-32"
  },
  {
    "city": "City-UAE-33",
    "state": "Abu Dhabi",
    "country": "UAE",
    "lat": 64.3223,
    "lng": -99.8251,
    "city_key": "uae|abu dhabi|city-uae-33"
  },
  {
    "city": "City-Singapore-34",
    "state": "Singapore",
    "country": "Singapore",
    "lat": -0.4372,
    "lng": -106.6005,
    "city_key": "singapore|singapore|city-singapore-34"
  },
  {
    "city": "City-France-35",
    "state": "Ile-de-France",
    "country": "France",
    "lat": 66.2071,
    "lng": 131.8951,
    "city_key": "france|ile-de-france|city-france-35"
  },
  {
    "city": "City-Germany-36",
    "state": "Hesse",
    "country": "Germany",
    "lat": -37.9715,
    "lng": -151.7395,
    "city_key": "germany|hesse|city-germany-36"
  },
  {
    "city": "City-Japan-37",
    "state": "Tokyo",
    "country": "Japan",
    "lat": 26.4963,
    "lng": 119.3234,
    "city_key": "japan|tokyo|city-japan-37"
  },
  {
    "city": "City-Japan-38",
    "state": "Tokyo",
    "country": "Japan",
    "lat": -54.771,
    "lng": 162.6344,
    "city_key": "japan|tokyo|city-japan-38"
  },
  {
    "city": "City-UK-39",
    "state": "England",
    "country": "UK",
    "lat": 26.1728,
    "lng": 116.9633,
    "city_key": "uk|england|city-uk-39"
  },
  {
    "city": "City-UK-40",
    "state": "England",
    "country": "UK",
    "lat": 13.6078,
    "lng": 31.4324,
    "city_key": "uk|england|city-uk-40"
  },
  {
    "city": "City-UK-41",
    "state": "Scotland",
    "country": "UK",
    "lat": -15.4557,
    "lng": 7.0642,
    "city_key": "uk|scotland|city-uk-41"
  },
  {
    "city": "City-Canada-42",
    "state": "Manitoba",
    "country": "Canada",
    "lat": 33.1849,
    "lng": 6.7916,
    "city_key": "canada|manitoba|city-canada-42"
  },
  {
    "city": "City-Japan-43",
    "state": "Aichi",
    "country": "Japan",
    "lat": -40.2549,
    "lng": 117.699,
    "city_key": "japan|aichi|city-japan-43"
  },
  {
    "city": "City-Japan-44",
    "state": "Osaka",
    "country": "Japan",
    "lat": 40.3234,
    "lng": 101.9023,
    "city_key": "japan|osaka|city-japan-44"
  },
  {
    "city": "City-India-45",
    "state": "Delhi",
    "country": "India",
    "lat": 47.2829,
    "lng": -147.7483,
    "city_key": "india|delhi|city-india-45"
  },
  {
    "city": "City-USA-46",
    "state": "Florida",
    "country": "USA",
    "lat": 18.9449,
    "lng": 13.3998,
    "city_key": "usa|florida|city-usa-46"
  },
  {
    "city": "City-USA-47",
    "state": "Washington",
    "country": "USA",
    "lat": 17.0025,
    "lng": 79.0394,
    "city_key": "usa|washington|city-usa-47"
  },
  {
    "city": "City-SouthKorea-48",
    "state": "Busan",
    "country": "South Korea",
    "lat": 48.0026,
    "lng": 5.7306,
    "city_key": "south korea|busan|city-southkorea-48"
  },
  {
    "city": "City-China-49",
    "state": "Zhejiang",
    "country": "China",
    "lat": 29.7336,
    "lng": 150.5261,
    "city_key": "china|zhejiang|city-china-49"
  },
  {
    "city": "City-Germany-50",
    "state": "Hamburg",
    "country": "Germany",
    "lat": 3.0009,
    "lng": -53.4932,
    "city_key": "germany|hamburg|city-germany-50"
  },
  {
    "city": "City-Australia-51",
    "state": "Queensland",
    "country": "Australia",
    "lat": -20.156,
    "lng": 147.3973,
    "city_key": "australia|queensland|city-australia-51"
  },
  {
    "city": "City-Germany-52",
    "state": "Bavaria",
    "country": "Germany",
    "lat": -56.3792,
    "lng": -52.8115,
    "city_key": "germany|bavaria|city-germany-52"
  },
  {
    "city": "City-Australia-53",
    "state": "Victoria",
    "country": "Australia",
    "lat": 45.326,
    "lng": -122.7119,
    "city_key": "australia|victoria|city-australia-53"
  },
  {
    "city": "City-Singapore-54",
    "state": "Singapore",
    "country": "Singapore",
    "lat": 4.239,
    "lng": 24.4069,
    "city_key": "singapore|singapore|city-singapore-54"
  },
  {
    "city": "City-Brazil-55",
    "state": "Sao Paulo",
    "country": "Brazil",
    "lat": 68.8159,
    "lng": -136.9598,
    "city_key": "brazil|sao paulo|city-brazil-55"
  },
  {
    "city": "City-USA-56",
    "state": "New York",
    "country": "USA",
    "lat": -62.1737,
    "lng": -39.1531,
    "city_key": "usa|new york|city-usa-56"
  },
  {
    "city": "City-Brazil-57",
    "state": "Rio de Janeiro",
    "country": "Brazil",
    "lat": -4.8119,
    "lng": 45.2778,
    "city_key": "brazil|rio de janeiro|city-brazil-57"
  },
  {
    "city": "City-China-58",
    "state": "Guangdong",
    "country": "China",
    "lat": -41.4676,
    "lng": -159.7581,
    "city_key": "china|guangdong|city-china-58"
  },
  {
    "city": "City-UAE-59",
    "state": "Dubai",
    "country": "UAE",
    "lat": 8.4496,
    "lng": 58.5162,
    "city_key": "uae|dubai|city-uae-59"
  },
  {
    "city": "City-Germany-60",
    "state": "Berlin",
    "country": "Germany",
    "lat": 36.6846,
    "lng": 80.4551,
    "city_key": "germany|berlin|city-germany-60"
  },
  {
    "city": "City-UK-61",
    "state": "England",
    "country": "UK",
    "lat": -7.8753,
    "lng": 111.6692,
    "city_key": "uk|england|city-uk-61"
  },
  {
    "city": "City-Australia-62",
    "state": "New South Wales",
    "country": "Australia",
    "lat": 16.0973,
    "lng": -39.5672,
    "city_key": "australia|new south wales|city-australia-62"
  },
  {
    "city": "City-China-63",
    "state": "Hubei",
    "country": "China",
    "lat": -65.6037,
    "lng": -21.5703,
    "city_key": "china|hubei|city-china-63"
  },
  {
    "city": "City-USA-64",
    "state": "Arizona",
    "country": "USA",
    "lat": 43.4896,
    "lng": 97.6437,
    "city_key": "usa|arizona|city-usa-64"
  },
  {
    "city": "City-UAE-65",
    "state": "Dubai",
    "country": "UAE",
    "lat": 47.6455,
    "lng": 146.188,
    "city_key": "uae|dubai|city-uae-65"
  },
  {
    "city": "City-UK-66",
    "state": "Scotland",
    "country": "UK",
    "lat": 16.8231,
    "lng": 114.3507,
    "city_key": "uk|scotland|city-uk-66"
  },
  {
    "city": "City-UAE-67",
    "state": "Dubai",
    "country": "UAE",
    "lat": -10.2288,
    "lng": 87.5656,
    "city_key": "uae|dubai|city-uae-67"
  },
  {
    "city": "City-Brazil-68",
    "state": "Rio de Janeiro",
    "country": "Brazil",
    "lat": 42.7938,
    "lng": -13.2196,
    "city_key": "brazil|rio de janeiro|city-brazil-68"
  },
  {
    "city": "City-SouthKorea-69",
    "state": "Busan",
    "country": "South Korea",
    "lat": 26.8574,
    "lng": -167.524,
    "city_key": "south korea|busan|city-southkorea-69"
  },
  {
    "city": "City-China-70",
    "state": "Guangdong",
    "country": "China",
    "lat": 11.7884,
    "lng": -163.6221,
    "city_key": "china|guangdong|city-china-70"
  },
  {
    "city": "City-Canada-71",
    "state": "Alberta",
    "country": "Canada",
    "lat": 54.9204,
    "lng": -37.2218,
    "city_key": "canada|alberta|city-canada-71"
  },
  {
    "city": "City-China-72",
    "state": "Beijing",
    "country": "China",
    "lat": 55.7892,
    "lng": 91.5376,
    "city_key": "china|beijing|city-china-72"
  },
  {
    "city": "City-Canada-73",
    "state": "Manitoba",
    "country": "Canada",
    "lat": 3.0582,
    "lng": 94.6678,
    "city_key": "canada|manitoba|city-canada-73"
  },
  {
    "city": "City-Singapore-74",
    "state": "Singapore",
    "country": "Singapore",
    "lat": -18.5382,
    "lng": -124.9616,
    "city_key": "singapore|singapore|city-singapore-74"
  },
  {
    "city": "City-USA-75",
    "state": "Massachusetts",
    "country": "USA",
    "lat": 54.1342,
    "lng": -87.5041,
    "city_key": "usa|massachusetts|city-usa-75"
  },
  {
    "city": "City-China-76",
    "state": "Shanghai",
    "country": "China",
    "lat": -46.2264,
    "lng": -99.7726,
    "city_key": "china|shanghai|city-china-76"
  },
  {
    "city": "City-China-77",
    "state": "Hubei",
    "country": "China",
    "lat": 20.3185,
    "lng": -158.2949,
    "city_key": "china|hubei|city-china-77"
  },
  {
    "city": "City-India-78",
    "state": "Karnataka",
    "country": "India",
    "lat": 7.4657,
    "lng": 160.7843,
    "city_key": "india|karnataka|city-india-78"
  },
  {
    "city": "City-USA-79",
    "state": "Texas",
    "country": "USA",
    "lat": 29.3285,
    "lng": -35.8856,
    "city_key": "usa|texas|city-usa-79"
  },
  {
    "city": "City-Australia-80",
    "state": "Queensland",
    "country": "Australia",
    "lat": -29.7665,
    "lng": -44.6808,
    "city_key": "australia|queensland|city-australia-80"
  },
  {
    "city": "City-India-81",
    "state": "Maharashtra",
    "country": "India",
    "lat": -41.1494,
    "lng": -77.5646,
    "city_key": "india|maharashtra|city-india-81"
  },
  {
    "city": "City-France-82",
    "state": "Auvergne-Rhone-Alpes",
    "country": "France",
    "lat": 41.3884,
    "lng": 162.304,
    "city_key": "france|auvergne-rhone-alpes|city-france-82"
  },
  {
    "city": "City-Australia-83",
    "state": "Victoria",
    "country": "Australia",
    "lat": 47.1164,
    "lng": -151.0659,
    "city_key": "australia|victoria|city-australia-83"
  },
  {
    "city": "City-SouthKorea-84",
    "state": "Busan",
    "country": "South Korea",
    "lat": -25.4852,
    "lng": 149.3473,
    "city_key": "south korea|busan|city-southkorea-84"
  },
  {
    "city": "City-Canada-85",
    "state": "Quebec",
    "country": "Canada",
    "lat": 0.7664,
    "lng": -134.5594,
    "city_key": "canada|quebec|city-canada-85"
  },
  {
    "city": "City-Brazil-86",
    "state": "Sao Paulo",
    "country": "Brazil",
    "lat": 35.4478,
    "lng": 40.7343,
    "city_key": "brazil|sao paulo|city-brazil-86"
  },
  {
    "city": "City-Brazil-87",
    "state": "Sao Paulo",
    "country": "Brazil",
    "lat": 62.7716,
    "lng": -73.6041,
    "city_key": "brazil|sao paulo|city-brazil-87"
  },
  {
    "city": "City-China-88",
    "state": "Jiangsu",
    "country": "China",
    "lat": -29.0656,
    "lng": 73.9531,
    "city_key": "china|jiangsu|city-china-88"
  },
  {
    "city": "City-Canada-89",
    "state": "Ontario",
    "country": "Canada",
    "lat": -26.2877,
    "lng": -78.2406,
    "city_key": "canada|ontario|city-canada-89"
  },
  {
    "city": "City-Brazil-90",
    "state": "Sao Paulo",
    "country": "Brazil",
    "lat": 41.1006,
    "lng": 115.2018,
    "city_key": "brazil|sao paulo|city-brazil-90"
  },
  {
    "city": "City-SouthKorea-91",
    "state": "Seoul",
    "country": "South Korea",
    "lat": -13.7322,
    "lng": -141.9277,
    "city_key": "south korea|seoul|city-southkorea-91"
  },
  {
    "city": "City-Singapore-92",
    "state": "Singapore",
    "country": "Singapore",
    "lat": -2.9544,
    "lng": 53.3954,
    "city_key": "singapore|singapore|city-singapore-92"
  },
  {
    "city": "City-USA-93",
    "state": "California",
    "country": "USA",
    "lat": 67.5144,
    "lng": 41.5681,
    "city_key": "usa|california|city-usa-93"
  },
  {
    "city": "City-China-94",
    "state": "Hubei",
    "country": "China",
    "lat": 68.3635,
    "lng": 8.9239,
    "city_key": "china|hubei|city-china-94"
  },
  {
    "city": "City-Singapore-95",
    "state": "Singapore",
    "country": "Singapore",
    "lat": -14.3049,
    "lng": 69.9645,
    "city_key": "singapore|singapore|city-singapore-95"
  },
  {
    "city": "City-USA-96",
    "state": "Florida",
    "country": "USA",
    "lat": 4.4047,
    "lng": -162.5858,
    "city_key": "usa|florida|city-usa-96"
  },
  {
    "city": "City-UAE-97",
    "state": "Dubai",
    "country": "UAE",
    "lat": 17.1354,
    "lng": -46.5667,
    "city_key": "uae|dubai|city-uae-97"
  },
  {
    "city": "City-UAE-98",
    "state": "Abu Dhabi",
    "country": "UAE",
    "lat": 43.8503,
    "lng": -118.6589,
    "city_key": "uae|abu dhabi|city-uae-98"
  },
  {
    "city": "City-UAE-99",
    "state": "Dubai",
    "country": "UAE",
    "lat": -5.8368,
    "lng": 125.5828,
    "city_key": "uae|dubai|city-uae-99"
  },
  {
    "city": "City-France-100",
    "state": "Auvergne-Rhone-Alpes",
    "country": "France",
    "lat": 55.8165,
    "lng": -96.8948,
    "city_key": "france|auvergne-rhone-alpes|city-france-100"
  },
  {
    "city": "City-Japan-101",
    "state": "Osaka",
    "country": "Japan",
    "lat": 41.983,
    "lng": -20.7615,
    "city_key": "japan|osaka|city-japan-101"
  },
  {
    "city": "City-Germany-102",
    "state": "Berlin",
    "country": "Germany",
    "lat": 11.4701,
    "lng": -121.8565,
    "city_key": "germany|berlin|city-germany-102"
  },
  {
    "city": "City-UAE-103",
    "state": "Dubai",
    "country": "UAE",
    "lat": -43.0637,
    "lng": 107.9794,
    "city_key": "uae|dubai|city-uae-103"
  },
  {
    "city": "City-Australia-104",
    "state": "Queensland",
    "country": "Australia",
    "lat": 3.7253,
    "lng": 1.6685,
    "city_key": "australia|queensland|city-australia-104"
  },
  {
    "city": "City-France-105",
    "state": "Ile-de-France",
    "country": "France",
    "lat": 1.7744,
    "lng": 102.0008,
    "city_key": "france|ile-de-france|city-france-105"
  },
  {
    "city": "City-Singapore-106",
    "state": "Singapore",
    "country": "Singapore",
    "lat": -33.5732,
    "lng": 102.1957,
    "city_key": "singapore|singapore|city-singapore-106"
  },
  {
    "city": "City-Japan-107",
    "state": "Aichi",
    "country": "Japan",
    "lat": 17.6589,
    "lng": 144.5859,
    "city_key": "japan|aichi|city-japan-107"
  },
  {
    "city": "City-France-108",
    "state": "Auvergne-Rhone-Alpes",
    "country": "France",
    "lat": 38.2691,
    "lng": -97.8043,
    "city_key": "france|auvergne-rhone-alpes|city-france-108"
  },
  {
    "city": "City-Germany-109",
    "state": "Berlin",
    "country": "Germany",
    "lat": 68.099,
    "lng": 133.2009,
    "city_key": "germany|berlin|city-germany-109"
  },
  {
    "city": "City-Germany-110",
    "state": "Berlin",
    "country": "Germany",
    "lat": -29.2616,
    "lng": 132.8672,
    "city_key": "germany|berlin|city-germany-110"
  },
  {
    "city": "City-UAE-111",
    "state": "Dubai",
    "country": "UAE",
    "lat": -43.2849,
    "lng": -120.5111,
    "city_key": "uae|dubai|city-uae-111"
  },
  {
    "city": "City-Singapore-112",
    "state": "Singapore",
    "country": "Singapore",
    "lat": -33.8361,
    "lng": -129.3564,
    "city_key": "singapore|singapore|city-singapore-112"
  },
  {
    "city": "City-China-113",
    "state": "Sichuan",
    "country": "China",
    "lat": 46.5055,
    "lng": -23.1204,
    "city_key": "china|sichuan|city-china-113"
  },
  {
    "city": "City-Japan-114",
    "state": "Tokyo",
    "country": "Japan",
    "lat": 57.8039,
    "lng": -143.077,
    "city_key": "japan|tokyo|city-japan-114"
  },
  {
    "city": "City-China-115",
    "state": "Shanghai",
    "country": "China",
    "lat": -1.2174,
    "lng": -84.7446,
    "city_key": "china|shanghai|city-china-115"
  },
  {
    "city": "City-China-116",
    "state": "Sichuan",
    "country": "China",
    "lat": -4.8278,
    "lng": 139.9957,
    "city_key": "china|sichuan|city-china-116"
  },
  {
    "city": "City-Japan-117",
    "state": "Aichi",
    "country": "Japan",
    "lat": 19.5369,
    "lng": 168.6528,
    "city_key": "japan|aichi|city-japan-117"
  },
  {
    "city": "City-Japan-118",
    "state": "Osaka",
    "country": "Japan",
    "lat": -26.5619,
    "lng": -96.1067,
    "city_key": "japan|osaka|city-japan-118"
  },
  {
    "city": "City-Germany-119",
    "state": "Hesse",
    "country": "Germany",
    "lat": -7.6999,
    "lng": -96.9063,
    "city_key": "germany|hesse|city-germany-119"
  },
  {
    "city": "City-China-120",
    "state": "Hubei",
    "country": "China",
    "lat": 2.1841,
    "lng": 123.6721,
    "city_key": "china|hubei|city-china-120"
  },
  {
    "city": "City-UAE-121",
    "state": "Dubai",
    "country": "UAE",
    "lat": -26.0083,
    "lng": 9.6861,
    "city_key": "uae|dubai|city-uae-121"
  },
  {
    "city": "City-Germany-122",
    "state": "Hesse",
    "country": "Germany",
    "lat": 17.1323,
    "lng": -139.3633,
    "city_key": "germany|hesse|city-germany-122"
  },
  {
    "city": "City-Germany-123",
    "state": "Hesse",
    "country": "Germany",
    "lat": -22.4613,
    "lng": 142.5898,
    "city_key": "germany|hesse|city-germany-123"
  },
  {
    "city": "City-SouthKorea-124",
    "state": "Seoul",
    "country": "South Korea",
    "lat": -44.8963,
    "lng": 124.848,
    "city_key": "south korea|seoul|city-southkorea-124"
  },
  {
    "city": "City-Singapore-125",
    "state": "Singapore",
    "country": "Singapore",
    "lat": 18.3014,
    "lng": 130.2901,
    "city_key": "singapore|singapore|city-singapore-125"
  },
  {
    "city": "City-SouthKorea-126",
    "state": "Seoul",
    "country": "South Korea",
    "lat": 18.5929,
    "lng": 151.9661,
    "city_key": "south korea|seoul|city-southkorea-126"
  },
  {
    "city": "City-France-127",
    "state": "Ile-de-France",
    "country": "France",
    "lat": 67.5282,
    "lng": 164.1867,
    "city_key": "france|ile-de-france|city-france-127"
  },
  {
    "city": "City-Singapore-128",
    "state": "Singapore",
    "country": "Singapore",
    "lat": 38.0821,
    "lng": 84.6165,
    "city_key": "singapore|singapore|city-singapore-128"
  },
  {
    "city": "City-SouthKorea-129",
    "state": "Seoul",
    "country": "South Korea",
    "lat": -53.7214,
    "lng": -161.4459,
    "city_key": "south korea|seoul|city-southkorea-129"
  },
  {
    "city": "City-UK-130",
    "state": "Scotland",
    "country": "UK",
    "lat": 31.7153,
    "lng": -163.7003,
    "city_key": "uk|scotland|city-uk-130"
  },
  {
    "city": "City-USA-131",
    "state": "Washington",
    "country": "USA",
    "lat": 44.8687,
    "lng": -1.9101,
    "city_key": "usa|washington|city-usa-131"
  },
  {
    "city": "City-UK-132",
    "state": "Scotland",
    "country": "UK",
    "lat": -27.7629,
    "lng": -169.5964,
    "city_key": "uk|scotland|city-uk-132"
  },
  {
    "city": "City-India-133",
    "state": "Delhi",
    "country": "India",
    "lat": 5.4711,
    "lng": 164.6916,
    "city_key": "india|delhi|city-india-133"
  },
  {
    "city": "City-Germany-134",
    "state": "Hamburg",
    "country": "Germany",
    "lat": -23.0131,
    "lng": 146.6036,
    "city_key": "germany|hamburg|city-germany-134"
  },
  {
    "city": "City-SouthKorea-135",
    "state": "Seoul",
    "country": "South Korea",
    "lat": 59.6419,
    "lng": -2.4103,
    "city_key": "south korea|seoul|city-southkorea-135"
  },
  {
    "city": "City-UK-136",
    "state": "England",
    "country": "UK",
    "lat": 14.8487,
    "lng": 33.6243,
    "city_key": "uk|england|city-uk-136"
  },
  {
    "city": "City-Germany-137",
    "state": "Berlin",
    "country": "Germany",
    "lat": -14.0868,
    "lng": -54.6433,
    "city_key": "germany|berlin|city-germany-137"
  },
  {
    "city": "City-Brazil-138",
    "state": "Sao Paulo",
    "country": "Brazil",
    "lat": -59.7468,
    "lng": 92.9187,
    "city_key": "brazil|sao paulo|city-brazil-138"
  },
  {
    "city": "City-India-139",
    "state": "Delhi",
    "country": "India",
    "lat": -6.9571,
    "lng": 117.2738,
    "city_key": "india|delhi|city-india-139"
  },
  {
    "city": "City-Japan-140",
    "state": "Osaka",
    "country": "Japan",
    "lat": -16.3269,
    "lng": -146.1133,
    "city_key": "japan|osaka|city-japan-140"
  },
  {
    "city": "City-SouthKorea-141",
    "state": "Busan",
    "country": "South Korea",
    "lat": 25.9618,
    "lng": 78.8904,
    "city_key": "south korea|busan|city-southkorea-141"
  },
  {
    "city": "City-USA-142",
    "state": "Arizona",
    "country": "USA",
    "lat": -12.1025,
    "lng": 145.9065,
    "city_key": "usa|arizona|city-usa-142"
  },
  {
    "city": "City-UK-143",
    "state": "Scotland",
    "country": "UK",
    "lat": 68.1437,
    "lng": -147.6233,
    "city_key": "uk|scotland|city-uk-143"
  },
  {
    "city": "City-Singapore-144",
    "state": "Singapore",
    "country": "Singapore",
    "lat": -69.0374,
    "lng": 14.8945,
    "city_key": "singapore|singapore|city-singapore-144"
  },
  {
    "city": "City-UAE-145",
    "state": "Dubai",
    "country": "UAE",
    "lat": -43.2506,
    "lng": 57.6946,
    "city_key": "uae|dubai|city-uae-145"
  },
  {
    "city": "City-Japan-146",
    "state": "Aichi",
    "country": "Japan",
    "lat": -34.6816,
    "lng": -31.8905,
    "city_key": "japan|aichi|city-japan-146"
  },
  {
    "city": "City-UAE-147",
    "state": "Dubai",
    "country": "UAE",
    "lat": -44.3297,
    "lng": 139.9005,
    "city_key": "uae|dubai|city-uae-147"
  },
  {
    "city": "City-India-148",
    "state": "Karnataka",
    "country": "India",
    "lat": 0.9113,
    "lng": -4.9251,
    "city_key": "india|karnataka|city-india-148"
  },
  {
    "city": "City-China-149",
    "state": "Guangdong",
    "country": "China",
    "lat": 38.546,
    "lng": -107.7195,
    "city_key": "china|guangdong|city-china-149"
  },
  {
    "city": "City-Germany-150",
    "state": "Bavaria",
    "country": "Germany",
    "lat": -0.9637,
    "lng": -157.0478,
    "city_key": "germany|bavaria|city-germany-150"
  },
  {
    "city": "City-Germany-151",
    "state": "Hesse",
    "country": "Germany",
    "lat": 16.2541,
    "lng": 63.0136,
    "city_key": "germany|hesse|city-germany-151"
  },
  {
    "city": "City-Australia-152",
    "state": "Queensland",
    "country": "Australia",
    "lat": -26.5821,
    "lng": 155.494,
    "city_key": "australia|queensland|city-australia-152"
  },
  {
    "city": "City-USA-153",
    "state": "California",
    "country": "USA",
    "lat": -37.3119,
    "lng": 138.3977,
    "city_key": "usa|california|city-usa-153"
  },
  {
    "city": "City-Japan-154",
    "state": "Aichi",
    "country": "Japan",
    "lat": 23.4945,
    "lng": -80.2751,
    "city_key": "japan|aichi|city-japan-154"
  },
  {
    "city": "City-UK-155",
    "state": "England",
    "country": "UK",
    "lat": 18.9698,
    "lng": -41.6029,
    "city_key": "uk|england|city-uk-155"
  },
  {
    "city": "City-Singapore-156",
    "state": "Singapore",
    "country": "Singapore",
    "lat": -5.0674,
    "lng": 127.5552,
    "city_key": "singapore|singapore|city-singapore-156"
  },
  {
    "city": "City-France-157",
    "state": "Auvergne-Rhone-Alpes",
    "country": "France",
    "lat": 63.3437,
    "lng": 168.9729,
    "city_key": "france|auvergne-rhone-alpes|city-france-157"
  },
  {
    "city": "City-Brazil-158",
    "state": "Rio de Janeiro",
    "country": "Brazil",
    "lat": 42.6037,
    "lng": 146.3134,
    "city_key": "brazil|rio de janeiro|city-brazil-158"
  },
  {
    "city": "City-Brazil-159",
    "state": "Sao Paulo",
    "country": "Brazil",
    "lat": -34.4002,
    "lng": -16.463,
    "city_key": "brazil|sao paulo|city-brazil-159"
  },
  {
    "city": "City-China-160",
    "state": "Shanghai",
    "country": "China",
    "lat": 59.3598,
    "lng": 159.0617,
    "city_key": "china|shanghai|city-china-160"
  },
  {
    "city": "City-Japan-161",
    "state": "Osaka",
    "country": "Japan",
    "lat": -40.6852,
    "lng": 117.7571,
    "city_key": "japan|osaka|city-japan-161"
  },
  {
    "city": "City-UAE-162",
    "state": "Abu Dhabi",
    "country": "UAE",
    "lat": -43.818,
    "lng": 130.1929,
    "city_key": "uae|abu dhabi|city-uae-162"
  },
  {
    "city": "City-Japan-163",
    "state": "Aichi",
    "country": "Japan",
    "lat": 5.0293,
    "lng": 81.8016,
    "city_key": "japan|aichi|city-japan-163"
  },
  {
    "city": "City-China-164",
    "state": "Jiangsu",
    "country": "China",
    "lat": 30.1828,
    "lng": 57.7162,
    "city_key": "china|jiangsu|city-china-164"
  },
  {
    "city": "City-UAE-165",
    "state": "Abu Dhabi",
    "country": "UAE",
    "lat": -25.6075,
    "lng": 77.5252,
    "city_key": "uae|abu dhabi|city-uae-165"
  },
  {
    "city": "City-SouthKorea-166",
    "state": "Seoul",
    "country": "South Korea",
    "lat": -41.1122,
    "lng": -46.5973,
    "city_key": "south korea|seoul|city-southkorea-166"
  },
  {
    "city": "City-UAE-167",
    "state": "Abu Dhabi",
    "country": "UAE",
    "lat": -35.1346,
    "lng": -2.6036,
    "city_key": "uae|abu dhabi|city-uae-167"
  },
  {
    "city": "City-Japan-168",
    "state": "Tokyo",
    "country": "Japan",
    "lat": 18.1603,
    "lng": -66.9207,
    "city_key": "japan|tokyo|city-japan-168"
  },
  {
    "city": "City-India-169",
    "state": "Karnataka",
    "country": "India",
    "lat": -6.3306,
    "lng": 148.6275,
    "city_key": "india|karnataka|city-india-169"
  },
  {
    "city": "City-SouthKorea-170",
    "state": "Seoul",
    "country": "South Korea",
    "lat": -17.9984,
    "lng": 44.4986,
    "city_key": "south korea|seoul|city-southkorea-170"
  },
  {
    "city": "City-SouthKorea-171",
    "state": "Busan",
    "country": "South Korea",
    "lat": -1.6371,
    "lng": -125.6727,
    "city_key": "south korea|busan|city-southkorea-171"
  },
  {
    "city": "City-Australia-172",
    "state": "Victoria",
    "country": "Australia",
    "lat": -49.3939,
    "lng": -48.3161,
    "city_key": "australia|victoria|city-australia-172"
  },
  {
    "city": "City-France-173",
    "state": "Auvergne-Rhone-Alpes",
    "country": "France",
    "lat": -1.9207,
    "lng": -12.6931,
    "city_key": "france|auvergne-rhone-alpes|city-france-173"
  },
  {
    "city": "City-India-174",
    "state": "Karnataka",
    "country": "India",
    "lat": -14.785,
    "lng": -86.4192,
    "city_key": "india|karnataka|city-india-174"
  },
  {
    "city": "City-Germany-175",
    "state": "Berlin",
    "country": "Germany",
    "lat": 11.9449,
    "lng": 165.3858,
    "city_key": "germany|berlin|city-germany-175"
  },
  {
    "city": "City-Australia-176",
    "state": "Victoria",
    "country": "Australia",
    "lat": -40.9175,
    "lng": 131.4984,
    "city_key": "australia|victoria|city-australia-176"
  },
  {
    "city": "City-China-177",
    "state": "Zhejiang",
    "country": "China",
    "lat": 1.3073,
    "lng": -67.9399,
    "city_key": "china|zhejiang|city-china-177"
  },
  {
    "city": "City-Australia-178",
    "state": "Victoria",
    "country": "Australia",
    "lat": -68.5942,
    "lng": -158.5898,
    "city_key": "australia|victoria|city-australia-178"
  },
  {
    "city": "City-Canada-179",
    "state": "Quebec",
    "country": "Canada",
    "lat": -13.3572,
    "lng": 72.4114,
    "city_key": "canada|quebec|city-canada-179"
  },
  {
    "city": "City-UAE-180",
    "state": "Abu Dhabi",
    "country": "UAE",
    "lat": -5.3087,
    "lng": -2.359,
    "city_key": "uae|abu dhabi|city-uae-180"
  },
  {
    "city": "City-France-181",
    "state": "Ile-de-France",
    "country": "France",
    "lat": -1.0361,
    "lng": -53.4981,
    "city_key": "france|ile-de-france|city-france-181"
  },
  {
    "city": "City-UK-182",
    "state": "England",
    "country": "UK",
    "lat": 26.6886,
    "lng": 72.3604,
    "city_key": "uk|england|city-uk-182"
  },
  {
    "city": "City-China-183",
    "state": "Jiangsu",
    "country": "China",
    "lat": -15.8435,
    "lng": 92.0918,
    "city_key": "china|jiangsu|city-china-183"
  },
  {
    "city": "City-Australia-184",
    "state": "New South Wales",
    "country": "Australia",
    "lat": 7.0517,
    "lng": 63.8763,
    "city_key": "australia|new south wales|city-australia-184"
  },
  {
    "city": "City-Japan-185",
    "state": "Tokyo",
    "country": "Japan",
    "lat": 18.1055,
    "lng": -145.0868,
    "city_key": "japan|tokyo|city-japan-185"
  },
  {
    "city": "City-Brazil-186",
    "state": "Rio de Janeiro",
    "country": "Brazil",
    "lat": -27.9881,
    "lng": -22.6628,
    "city_key": "brazil|rio de janeiro|city-brazil-186"
  },
  {
    "city": "City-Singapore-187",
    "state": "Singapore",
    "country": "Singapore",
    "lat": -1.5408,
    "lng": 4.0475,
    "city_key": "singapore|singapore|city-singapore-187"
  },
  {
    "city": "City-Canada-188",
    "state": "Manitoba",
    "country": "Canada",
    "lat": 29.5641,
    "lng": 121.341,
    "city_key": "canada|manitoba|city-canada-188"
  },
  {
    "city": "City-UAE-189",
    "state": "Abu Dhabi",
    "country": "UAE",
    "lat": -69.0822,
    "lng": 115.9086,
    "city_key": "uae|abu dhabi|city-uae-189"
  },
  {
    "city": "City-Canada-190",
    "state": "Alberta",
    "country": "Canada",
    "lat": -25.9859,
    "lng": -92.9063,
    "city_key": "canada|alberta|city-canada-190"
  },
  {
    "city": "City-France-191",
    "state": "Ile-de-France",
    "country": "France",
    "lat": -31.0666,
    "lng": 46.8214,
    "city_key": "france|ile-de-france|city-france-191"
  },
  {
    "city": "City-France-192",
    "state": "Ile-de-France",
    "country": "France",
    "lat": 68.5919,
    "lng": -167.117,
    "city_key": "france|ile-de-france|city-france-192"
  },
  {
    "city": "City-China-193",
    "state": "Sichuan",
    "country": "China",
    "lat": 65.1554,
    "lng": -46.8329,
    "city_key": "china|sichuan|city-china-193"
  },
  {
    "city": "City-Japan-194",
    "state": "Tokyo",
    "country": "Japan",
    "lat": 43.6952,
    "lng": -57.0993,
    "city_key": "japan|tokyo|city-japan-194"
  },
  {
    "city": "City-SouthKorea-195",
    "state": "Seoul",
    "country": "South Korea",
    "lat": 36.8024,
    "lng": 46.4894,
    "city_key": "south korea|seoul|city-southkorea-195"
  },
  {
    "city": "City-Brazil-196",
    "state": "Rio de Janeiro",
    "country": "Brazil",
    "lat": -34.0698,
    "lng": 127.598,
    "city_key": "brazil|rio de janeiro|city-brazil-196"
  },
  {
    "city": "City-Brazil-197",
    "state": "Rio de Janeiro",
    "country": "Brazil",
    "lat": -21.3092,
    "lng": 142.8449,
    "city_key": "brazil|rio de janeiro|city-brazil-197"
  },
  {
    "city": "City-India-198",
    "state": "Karnataka",
    "country": "India",
    "lat": -10.9425,
    "lng": -150.7013,
    "city_key": "india|karnataka|city-india-198"
  },
  {
    "city": "City-China-199",
    "state": "Hubei",
    "country": "China",
    "lat": -43.0483,
    "lng": -3.8354,
    "city_key": "china|hubei|city-china-199"
  },
  {
    "city": "City-China-200",
    "state": "Hubei",
    "country": "China",
    "lat": 41.4544,
    "lng": -96.9274,
    "city_key": "china|hubei|city-china-200"
  },
  {
    "city": "City-Germany-201",
    "state": "Bavaria",
    "country": "Germany",
    "lat": -25.0773,
    "lng": 159.1636,
    "city_key": "germany|bavaria|city-germany-201"
  },
  {
    "city": "City-Germany-202",
    "state": "Hesse",
    "country": "Germany",
    "lat": 22.3466,
    "lng": -6.425,
    "city_key": "germany|hesse|city-germany-202"
  },
  {
    "city": "City-Australia-203",
    "state": "Victoria",
    "country": "Australia",
    "lat": -19.1099,
    "lng": 46.1255,
    "city_key": "australia|victoria|city-australia-203"
  },
  {
    "city": "City-UAE-204",
    "state": "Dubai",
    "country": "UAE",
    "lat": 14.7487,
    "lng": 29.506,
    "city_key": "uae|dubai|city-uae-204"
  },
  {
    "city": "City-China-205",
    "state": "Guangdong",
    "country": "China",
    "lat": 67.9318,
    "lng": 168.8528,
    "city_key": "china|guangdong|city-china-205"
  },
  {
    "city": "City-Germany-206",
    "state": "Berlin",
    "country": "Germany",
    "lat": -55.9777,
    "lng": -75.6061,
    "city_key": "germany|berlin|city-germany-206"
  },
  {
    "city": "City-Germany-207",
    "state": "Berlin",
    "country": "Germany",
    "lat": 61.4597,
    "lng": 23.8506,
    "city_key": "germany|berlin|city-germany-207"
  },
  {
    "city": "City-India-208",
    "state": "Tamil Nadu",
    "country": "India",
    "lat": 3.3362,
    "lng": 146.5341,
    "city_key": "india|tamil nadu|city-india-208"
  },
  {
    "city": "City-India-209",
    "state": "Tamil Nadu",
    "country": "India",
    "lat": -26.7866,
    "lng": -143.7953,
    "city_key": "india|tamil nadu|city-india-209"
  },
  {
    "city": "City-Germany-210",
    "state": "Hamburg",
    "country": "Germany",
    "lat": 46.8177,
    "lng": -157.0409,
    "city_key": "germany|hamburg|city-germany-210"
  },
  {
    "city": "City-Japan-211",
    "state": "Tokyo",
    "country": "Japan",
    "lat": -2.5912,
    "lng": 155.2282,
    "city_key": "japan|tokyo|city-japan-211"
  },
  {
    "city": "City-Australia-212",
    "state": "Victoria",
    "country": "Australia",
    "lat": -62.3957,
    "lng": -133.0841,
    "city_key": "australia|victoria|city-australia-212"
  },
  {
    "city": "City-Singapore-213",
    "state": "Singapore",
    "country": "Singapore",
    "lat": -49.3326,
    "lng": 150.7383,
    "city_key": "singapore|singapore|city-singapore-213"
  },
  {
    "city": "City-India-214",
    "state": "Delhi",
    "country": "India",
    "lat": -7.4274,
    "lng": 16.0416,
    "city_key": "india|delhi|city-india-214"
  },
  {
    "city": "City-SouthKorea-215",
    "state": "Busan",
    "country": "South Korea",
    "lat": -57.0935,
    "lng": 158.6418,
    "city_key": "south korea|busan|city-southkorea-215"
  },
  {
    "city": "City-India-216",
    "state": "Maharashtra",
    "country": "India",
    "lat": 56.3394,
    "lng": 73.5822,
    "city_key": "india|maharashtra|city-india-216"
  },
  {
    "city": "City-USA-217",
    "state": "Arizona",
    "country": "USA",
    "lat": -7.0041,
    "lng": 121.6715,
    "city_key": "usa|arizona|city-usa-217"
  },
  {
    "city": "City-SouthKorea-218",
    "state": "Seoul",
    "country": "South Korea",
    "lat": -33.8568,
    "lng": -83.5905,
    "city_key": "south korea|seoul|city-southkorea-218"
  },
  {
    "city": "City-Japan-219",
    "state": "Tokyo",
    "country": "Japan",
    "lat": 48.4608,
    "lng": 121.7555,
    "city_key": "japan|tokyo|city-japan-219"
  },
  {
    "city": "City-Brazil-220",
    "state": "Sao Paulo",
    "country": "Brazil",
    "lat": 68.4586,
    "lng": -73.6539,
    "city_key": "brazil|sao paulo|city-brazil-220"
  },
  {
    "city": "City-Japan-221",
    "state": "Aichi",
    "country": "Japan",
    "lat": -66.225,
    "lng": -25.5086,
    "city_key": "japan|aichi|city-japan-221"
  },
  {
    "city": "City-India-222",
    "state": "Tamil Nadu",
    "country": "India",
    "lat": 2.8351,
    "lng": -37.5115,
    "city_key": "india|tamil nadu|city-india-222"
  },
  {
    "city": "City-USA-223",
    "state": "Washington",
    "country": "USA",
    "lat": -32.8219,
    "lng": 17.7873,
    "city_key": "usa|washington|city-usa-223"
  },
  {
    "city": "City-Singapore-224",
    "state": "Singapore",
    "country": "Singapore",
    "lat": 68.0973,
    "lng": 155.2372,
    "city_key": "singapore|singapore|city-singapore-224"
  },
  {
    "city": "City-Japan-225",
    "state": "Tokyo",
    "country": "Japan",
    "lat": -39.4536,
    "lng": -50.9221,
    "city_key": "japan|tokyo|city-japan-225"
  },
  {
    "city": "City-Singapore-226",
    "state": "Singapore",
    "country": "Singapore",
    "lat": -63.7317,
    "lng": -0.0998,
    "city_key": "singapore|singapore|city-singapore-226"
  },
  {
    "city": "City-Brazil-227",
    "state": "Sao Paulo",
    "country": "Brazil",
    "lat": 19.7258,
    "lng": -9.5157,
    "city_key": "brazil|sao paulo|city-brazil-227"
  },
  {
    "city": "City-SouthKorea-228",
    "state": "Seoul",
    "country": "South Korea",
    "lat": -60.0668,
    "lng": 36.2296,
    "city_key": "south korea|seoul|city-southkorea-228"
  },
  {
    "city": "City-USA-229",
    "state": "Washington",
    "country": "USA",
    "lat": -45.6445,
    "lng": 90.6429,
    "city_key": "usa|washington|city-usa-229"
  },
  {
    "city": "City-Australia-230",
    "state": "New South Wales",
    "country": "Australia",
    "lat": -66.8599,
    "lng": 87.9382,
    "city_key": "australia|new south wales|city-australia-230"
  },
  {
    "city": "City-Canada-231",
    "state": "Alberta",
    "country": "Canada",
    "lat": 16.4249,
    "lng": -118.5462,
    "city_key": "canada|alberta|city-canada-231"
  },
  {
    "city": "City-USA-232",
    "state": "Florida",
    "country": "USA",
    "lat": 15.607,
    "lng": -73.9143,
    "city_key": "usa|florida|city-usa-232"
  },
  {
    "city": "City-Germany-233",
    "state": "Berlin",
    "country": "Germany",
    "lat": 38.7141,
    "lng": -133.7622,
    "city_key": "germany|berlin|city-germany-233"
  },
  {
    "city": "City-Japan-234",
    "state": "Tokyo",
    "country": "Japan",
    "lat": -45.0843,
    "lng": -166.0776,
    "city_key": "japan|tokyo|city-japan-234"
  },
  {
    "city": "City-Brazil-235",
    "state": "Rio de Janeiro",
    "country": "Brazil",
    "lat": -38.0068,
    "lng": -25.2951,
    "city_key": "brazil|rio de janeiro|city-brazil-235"
  },
  {
    "city": "City-Brazil-236",
    "state": "Rio de Janeiro",
    "country": "Brazil",
    "lat": 17.9064,
    "lng": 3.815,
    "city_key": "brazil|rio de janeiro|city-brazil-236"
  },
  {
    "city": "City-India-237",
    "state": "Tamil Nadu",
    "country": "India",
    "lat": -3.4524,
    "lng": -84.7641,
    "city_key": "india|tamil nadu|city-india-237"
  },
  {
    "city": "City-Germany-238",
    "state": "Berlin",
    "country": "Germany",
    "lat": 38.3276,
    "lng": 129.0972,
    "city_key": "germany|berlin|city-germany-238"
  },
  {
    "city": "City-Canada-239",
    "state": "Quebec",
    "country": "Canada",
    "lat": 49.2754,
    "lng": -125.7322,
    "city_key": "canada|quebec|city-canada-239"
  },
  {
    "city": "City-Singapore-240",
    "state": "Singapore",
    "country": "Singapore",
    "lat": -24.3544,
    "lng": 94.0855,
    "city_key": "singapore|singapore|city-singapore-240"
  },
  {
    "city": "City-Germany-241",
    "state": "Hamburg",
    "country": "Germany",
    "lat": -60.5347,
    "lng": 78.131,
    "city_key": "germany|hamburg|city-germany-241"
  },
  {
    "city": "City-Germany-242",
    "state": "Berlin",
    "country": "Germany",
    "lat": -69.1209,
    "lng": -76.2766,
    "city_key": "germany|berlin|city-germany-242"
  },
  {
    "city": "City-UAE-243",
    "state": "Dubai",
    "country": "UAE",
    "lat": -23.3294,
    "lng": -95.3742,
    "city_key": "uae|dubai|city-uae-243"
  },
  {
    "city": "City-Australia-244",
    "state": "Queensland",
    "country": "Australia",
    "lat": 67.9466,
    "lng": 148.1439,
    "city_key": "australia|queensland|city-australia-244"
  },
  {
    "city": "City-India-245",
    "state": "Delhi",
    "country": "India",
    "lat": 30.5318,
    "lng": -141.789,
    "city_key": "india|delhi|city-india-245"
  },
  {
    "city": "City-USA-246",
    "state": "Florida",
    "country": "USA",
    "lat": -22.8333,
    "lng": -158.1827,
    "city_key": "usa|florida|city-usa-246"
  },
  {
    "city": "City-UK-247",
    "state": "England",
    "country": "UK",
    "lat": 3.3034,
    "lng": 148.0858,
    "city_key": "uk|england|city-uk-247"
  },
  {
    "city": "City-UK-248",
    "state": "England",
    "country": "UK",
    "lat": 3.8972,
    "lng": 87.9349,
    "city_key": "uk|england|city-uk-248"
  },
  {
    "city": "City-Singapore-249",
    "state": "Singapore",
    "country": "Singapore",
    "lat": -29.8197,
    "lng": 43.1192,
    "city_key": "singapore|singapore|city-singapore-249"
  },
  {
    "city": "City-Germany-250",
    "state": "Hamburg",
    "country": "Germany",
    "lat": -45.5489,
    "lng": -39.2412,
    "city_key": "germany|hamburg|city-germany-250"
  },
  {
    "city": "City-USA-251",
    "state": "Arizona",
    "country": "USA",
    "lat": -14.3007,
    "lng": -126.4829,
    "city_key": "usa|arizona|city-usa-251"
  },
  {
    "city": "City-SouthKorea-252",
    "state": "Seoul",
    "country": "South Korea",
    "lat": -8.4793,
    "lng": -120.3815,
    "city_key": "south korea|seoul|city-southkorea-252"
  },
  {
    "city": "City-SouthKorea-253",
    "state": "Seoul",
    "country": "South Korea",
    "lat": 52.2897,
    "lng": 26.8221,
    "city_key": "south korea|seoul|city-southkorea-253"
  },
  {
    "city": "City-UAE-254",
    "state": "Dubai",
    "country": "UAE",
    "lat": 69.4682,
    "lng": 90.4725,
    "city_key": "uae|dubai|city-uae-254"
  },
  {
    "city": "City-Australia-255",
    "state": "New South Wales",
    "country": "Australia",
    "lat": -55.5523,
    "lng": 91.8996,
    "city_key": "australia|new south wales|city-australia-255"
  },
  {
    "city": "City-Brazil-256",
    "state": "Rio de Janeiro",
    "country": "Brazil",
    "lat": 64.5839,
    "lng": -138.1717,
    "city_key": "brazil|rio de janeiro|city-brazil-256"
  },
  {
    "city": "City-France-257",
    "state": "Ile-de-France",
    "country": "France",
    "lat": -30.0651,
    "lng": 96.7632,
    "city_key": "france|ile-de-france|city-france-257"
  },
  {
    "city": "City-Brazil-258",
    "state": "Sao Paulo",
    "country": "Brazil",
    "lat": -54.15,
    "lng": -52.5533,
    "city_key": "brazil|sao paulo|city-brazil-258"
  },
  {
    "city": "City-UAE-259",
    "state": "Abu Dhabi",
    "country": "UAE",
    "lat": -38.1321,
    "lng": 48.1019,
    "city_key": "uae|abu dhabi|city-uae-259"
  },
  {
    "city": "City-Brazil-260",
    "state": "Sao Paulo",
    "country": "Brazil",
    "lat": 33.2559,
    "lng": -168.1877,
    "city_key": "brazil|sao paulo|city-brazil-260"
  },
  {
    "city": "City-France-261",
    "state": "Auvergne-Rhone-Alpes",
    "country": "France",
    "lat": -58.1958,
    "lng": -8.1393,
    "city_key": "france|auvergne-rhone-alpes|city-france-261"
  },
  {
    "city": "City-Germany-262",
    "state": "Hamburg",
    "country": "Germany",
    "lat": -48.107,
    "lng": -53.3283,
    "city_key": "germany|hamburg|city-germany-262"
  },
  {
    "city": "City-UK-263",
    "state": "Scotland",
    "country": "UK",
    "lat": 38.5389,
    "lng": -109.805,
    "city_key": "uk|scotland|city-uk-263"
  },
  {
    "city": "City-Canada-264",
    "state": "British Columbia",
    "country": "Canada",
    "lat": -16.4865,
    "lng": 100.4746,
    "city_key": "canada|british columbia|city-canada-264"
  },
  {
    "city": "City-USA-265",
    "state": "Washington",
    "country": "USA",
    "lat": -32.8908,
    "lng": -78.2094,
    "city_key": "usa|washington|city-usa-265"
  },
  {
    "city": "City-UK-266",
    "state": "Scotland",
    "country": "UK",
    "lat": -68.4072,
    "lng": 89.4158,
    "city_key": "uk|scotland|city-uk-266"
  },
  {
    "city": "City-France-267",
    "state": "Auvergne-Rhone-Alpes",
    "country": "France",
    "lat": 16.5941,
    "lng": -39.6406,
    "city_key": "france|auvergne-rhone-alpes|city-france-267"
  },
  {
    "city": "City-Singapore-268",
    "state": "Singapore",
    "country": "Singapore",
    "lat": -67.0797,
    "lng": -23.9913,
    "city_key": "singapore|singapore|city-singapore-268"
  },
  {
    "city": "City-India-269",
    "state": "Tamil Nadu",
    "country": "India",
    "lat": -22.7991,
    "lng": 57.2502,
    "city_key": "india|tamil nadu|city-india-269"
  },
  {
    "city": "City-China-270",
    "state": "Zhejiang",
    "country": "China",
    "lat": 8.0486,
    "lng": 20.7309,
    "city_key": "china|zhejiang|city-china-270"
  },
  {
    "city": "City-Canada-271",
    "state": "Quebec",
    "country": "Canada",
    "lat": -36.6548,
    "lng": 53.4638,
    "city_key": "canada|quebec|city-canada-271"
  },
  {
    "city": "City-India-272",
    "state": "Maharashtra",
    "country": "India",
    "lat": 67.2822,
    "lng": 143.49,
    "city_key": "india|maharashtra|city-india-272"
  },
  {
    "city": "City-SouthKorea-273",
    "state": "Seoul",
    "country": "South Korea",
    "lat": -38.9151,
    "lng": -157.4893,
    "city_key": "south korea|seoul|city-southkorea-273"
  },
  {
    "city": "City-Australia-274",
    "state": "Queensland",
    "country": "Australia",
    "lat": -37.2291,
    "lng": 130.1176,
    "city_key": "australia|queensland|city-australia-274"
  },
  {
    "city": "City-Germany-275",
    "state": "Bavaria",
    "country": "Germany",
    "lat": 51.0364,
    "lng": -72.7025,
    "city_key": "germany|bavaria|city-germany-275"
  },
  {
    "city": "City-UK-276",
    "state": "Scotland",
    "country": "UK",
    "lat": -56.5821,
    "lng": -96.167,
    "city_key": "uk|scotland|city-uk-276"
  },
  {
    "city": "City-France-277",
    "state": "Ile-de-France",
    "country": "France",
    "lat": -31.9866,
    "lng": -20.0186,
    "city_key": "france|ile-de-france|city-france-277"
  },
  {
    "city": "City-Singapore-278",
    "state": "Singapore",
    "country": "Singapore",
    "lat": 56.1298,
    "lng": -79.1311,
    "city_key": "singapore|singapore|city-singapore-278"
  },
  {
    "city": "City-Japan-279",
    "state": "Osaka",
    "country": "Japan",
    "lat": 60.4315,
    "lng": -93.9602,
    "city_key": "japan|osaka|city-japan-279"
  },
  {
    "city": "City-Singapore-280",
    "state": "Singapore",
    "country": "Singapore",
    "lat": 34.4916,
    "lng": -64.4009,
    "city_key": "singapore|singapore|city-singapore-280"
  },
  {
    "city": "City-Australia-281",
    "state": "Queensland",
    "country": "Australia",
    "lat": 62.9215,
    "lng": -69.4184,
    "city_key": "australia|queensland|city-australia-281"
  },
  {
    "city": "City-SouthKorea-282",
    "state": "Busan",
    "country": "South Korea",
    "lat": 39.9383,
    "lng": -107.3939,
    "city_key": "south korea|busan|city-southkorea-282"
  },
  {
    "city": "City-UAE-283",
    "state": "Dubai",
    "country": "UAE",
    "lat": -18.2971,
    "lng": 20.7058,
    "city_key": "uae|dubai|city-uae-283"
  },
  {
    "city": "City-France-284",
    "state": "Ile-de-France",
    "country": "France",
    "lat": -31.5597,
    "lng": -73.5493,
    "city_key": "france|ile-de-france|city-france-284"
  },
  {
    "city": "City-Brazil-285",
    "state": "Sao Paulo",
    "country": "Brazil",
    "lat": 22.2308,
    "lng": -13.1063,
    "city_key": "brazil|sao paulo|city-brazil-285"
  }
]